{
    "director": "richon",
    "reserved_names": [
        "verix",
        "r1ch0n",
        "rich0n",
        "richon",
        "r1chon",
        "orbe",
        "admin",
        "dev",
        "verixdespiertatualma",
        "richon2025",
        "richon2026",
        "RICHON2026",
        "Richon2026",
        "_richon2026_",
        "admin_richon2026",
        "master_richon2026",
        "R1CH0N",
        "R1ch0n",
        "_r1ch0n_",
        "admin_r1ch0n",
        "master_r1ch0n",
        "R1CHON",
        "R1chon",
        "_r1chon_",
        "admin_r1chon",
        "master_r1chon",
        "RICH0N",
        "Rich0n",
        "_rich0n_",
        "admin_rich0n",
        "master_rich0n"
    ],
    "hash_key1": "b00fb68debc63dc5e39c6ccbb491350aabbceaf24d82698944a765fa4f0ac05e",
    "hash_key2": "f871328e6a1b3e71bc99a6f45a0bbab546aed53c6f8e4123f11494be032a4ccd",
    "factor3_users": [],
    "usuarios_adicionales": []
}